{
  "total_terms": 13,
  "core": 5,
  "domain": 7,
  "aux": 1,
  "draft_ratio": 0.0,
  "unmapped_ratio": 0.0,
  "queue_pending": 0,
  "queue_accepted": 2,
  "queue_merged": 2,
  "conflicts_open": 0,
  "ambiguities_high": 1,
  "ambiguities_total": 1,
  "decisions_lines": 119,
  "decisions_active": 8,
  "claims_lines": 64,
  "updated_at": "2026-01-29T22:58:12Z",
  "budget_utilization": {
    "total": 16.25,
    "core": 25.0,
    "domain": 23.33,
    "aux": 3.33
  },
  "last_run_type": "janitor_concept",
  "system_health": "healthy",
  "total_invariants": 14,
  "total_mappings": 11,
  "bloat_status": "healthy",
  "bloat_percentage": 16.25,
  "gc_actions_taken": [
    "janitor_check_2026-01-29T22:58:12Z: no_issues_found"
  ]
}
